{
    "time": 5000,
    "weather": "clear",
    "biome": "flower_forest",
    "world": "overworld",
    "block": "bee_nest",
    "inventory": {
        "minecraft:dirt": 10,
        "minecraft:campfire": 1,
        "minecraft:glass_bottle": 5,
        "minecraft:shears": 1,
        "minecraft:bread": 16,
        "minecraft:oak_sapling": 5,
        "minecraft:torch": 20
    },
    "underground": 0,
    "armor": {
        "armor.head": "",
        "armor.chest": "",
        "armor.legs": "",
        "armor.feet": "",
        "weapon.mainhand": "minecraft:iron_axe{Enchantments:[{id:silk_touch, lvl:1}]}",
        "weapon.offhand": ""
    },
    "generate_block": false
}